{
  "0": {
    "balance": 794.5879408089982,
    "positions": [
      {
        "symbol": "ONTUSDT",
        "entry_price": 0.0841,
        "margin": 79.45879408089982,
        "amount": 2834.4397412925027,
        "leverage": 3.0,
        "entry_time": 1774915560,
        "max_price": 0.0841,
        "min_price": 0.0769,
        "side": "SHORT"
      },
      {
        "symbol": "NOMUSDT",
        "entry_price": 0.003523,
        "margin": 79.45879408089982,
        "amount": 67662.89589630981,
        "leverage": 3.0,
        "entry_time": 1774915560,
        "max_price": 0.003523,
        "min_price": 0.003259,
        "side": "SHORT"
      },
      {
        "symbol": "DUSDT",
        "entry_price": 0.006619,
        "margin": 79.45879408089982,
        "amount": 36013.95712988359,
        "leverage": 3.0,
        "entry_time": 1774915560,
        "max_price": 0.007143,
        "min_price": 0.006569,
        "side": "SHORT"
      },
      {
        "symbol": "DAMUSDT",
        "entry_price": 0.03515,
        "margin": 79.45879408089982,
        "amount": 6781.6893952403825,
        "leverage": 3.0,
        "entry_time": 1774915560,
        "max_price": 0.03673,
        "min_price": 0.0349,
        "side": "SHORT"
      },
      {
        "symbol": "RIVERUSDT",
        "entry_price": 16.441,
        "margin": 79.45879408089982,
        "amount": 14.49889801366702,
        "leverage": 3.0,
        "entry_time": 1774915560,
        "max_price": 17.519,
        "min_price": 16.441,
        "side": "SHORT"
      },
      {
        "symbol": "FHEUSDT",
        "entry_price": 0.01873,
        "margin": 79.45879408089982,
        "amount": 12726.98250094498,
        "leverage": 3.0,
        "entry_time": 1774915560,
        "max_price": 0.02005,
        "min_price": 0.01873,
        "side": "SHORT"
      },
      {
        "symbol": "USUSDT",
        "entry_price": 0.003899,
        "margin": 79.45879408089982,
        "amount": 61137.82565855334,
        "leverage": 3.0,
        "entry_time": 1774915560,
        "max_price": 0.004289,
        "min_price": 0.003894,
        "side": "SHORT"
      },
      {
        "symbol": "GOATUSDT",
        "entry_price": 0.01801,
        "margin": 79.45879408089982,
        "amount": 13235.779136185422,
        "leverage": 3.0,
        "entry_time": 1774915560,
        "max_price": 0.01852,
        "min_price": 0.01801,
        "side": "SHORT"
      },
      {
        "symbol": "ONGUSDT",
        "entry_price": 0.06421,
        "margin": 79.45879408089982,
        "amount": 3712.4494976280866,
        "leverage": 3.0,
        "entry_time": 1774915560,
        "max_price": 0.06421,
        "min_price": 0.06191,
        "side": "SHORT"
      },
      {
        "symbol": "DOODUSDT",
        "entry_price": 0.003072,
        "margin": 79.45879408089982,
        "amount": 77596.47859462873,
        "leverage": 3.0,
        "entry_time": 1774915560,
        "max_price": 0.003083,
        "min_price": 0.002983,
        "side": "SHORT"
      }
    ],
    "last_trade_date": "2026-03-31",
    "total_invested": 1000.0,
    "liquidation_count": 0
  },
  "1": {
    "balance": 1977.5548553116812,
    "positions": [],
    "last_trade_date": "2026-03-31",
    "total_invested": 0.0,
    "liquidation_count": 0
  },
  "2": {
    "balance": 848.0867945444569,
    "positions": [],
    "last_trade_date": "2026-03-31",
    "total_invested": 0.0,
    "liquidation_count": 0
  },
  "3": {
    "balance": 1041.9532166511517,
    "positions": [
      {
        "symbol": "RIVERUSDT",
        "entry_price": 17.444,
        "margin": 104.19532166511517,
        "amount": 17.919397213674934,
        "leverage": 3.0,
        "entry_time": 1774927910,
        "max_price": 17.519,
        "min_price": 17.072,
        "side": "SHORT"
      },
      {
        "symbol": "DUSDT",
        "entry_price": 0.007143,
        "margin": 104.19532166511517,
        "amount": 43761.15987615085,
        "leverage": 3.0,
        "entry_time": 1774927910,
        "max_price": 0.007143,
        "min_price": 0.006569,
        "side": "SHORT"
      },
      {
        "symbol": "GUSDT",
        "entry_price": 0.004151,
        "margin": 104.19532166511517,
        "amount": 75303.77378832703,
        "leverage": 3.0,
        "entry_time": 1774927910,
        "max_price": 0.004313,
        "min_price": 0.004151,
        "side": "SHORT"
      },
      {
        "symbol": "FHEUSDT",
        "entry_price": 0.02005,
        "margin": 104.19532166511517,
        "amount": 15590.322443658133,
        "leverage": 3.0,
        "entry_time": 1774927910,
        "max_price": 0.02005,
        "min_price": 0.01942,
        "side": "SHORT"
      },
      {
        "symbol": "DAMUSDT",
        "entry_price": 0.0349,
        "margin": 104.19532166511517,
        "amount": 8956.61790817609,
        "leverage": 3.0,
        "entry_time": 1774927910,
        "max_price": 0.03673,
        "min_price": 0.0349,
        "side": "SHORT"
      },
      {
        "symbol": "USUSDT",
        "entry_price": 0.003894,
        "margin": 104.19532166511517,
        "amount": 80273.74550471123,
        "leverage": 3.0,
        "entry_time": 1774927910,
        "max_price": 0.004289,
        "min_price": 0.003894,
        "side": "SHORT"
      },
      {
        "symbol": "BANUSDT",
        "entry_price": 0.0661,
        "margin": 104.19532166511517,
        "amount": 4728.985854695091,
        "leverage": 3.0,
        "entry_time": 1774927910,
        "max_price": 0.06614,
        "min_price": 0.06541,
        "side": "SHORT"
      },
      {
        "symbol": "AIOTUSDT",
        "entry_price": 0.01079,
        "margin": 104.19532166511517,
        "amount": 28969.968952302646,
        "leverage": 3.0,
        "entry_time": 1774927910,
        "max_price": 0.0135,
        "min_price": 0.01079,
        "side": "SHORT"
      },
      {
        "symbol": "CYSUSDT",
        "entry_price": 0.3917,
        "margin": 104.19532166511517,
        "amount": 798.0239085916404,
        "leverage": 3.0,
        "entry_time": 1774927910,
        "max_price": 0.3917,
        "min_price": 0.3485,
        "side": "SHORT"
      },
      {
        "symbol": "GOATUSDT",
        "entry_price": 0.01832,
        "margin": 104.19532166511517,
        "amount": 17062.552674418424,
        "leverage": 3.0,
        "entry_time": 1774927910,
        "max_price": 0.01852,
        "min_price": 0.01831,
        "side": "SHORT"
      }
    ],
    "last_trade_date": "2026-03-31",
    "total_invested": 1000.0,
    "liquidation_count": 0
  },
  "4": {
    "balance": 1270.0715620414142,
    "positions": [],
    "last_trade_date": "2026-03-31",
    "total_invested": 0.0,
    "liquidation_count": 1
  },
  "5": {
    "balance": 1720.927840848713,
    "positions": [
      {
        "symbol": "AIOTUSDT",
        "entry_price": 0.01325,
        "margin": 172.0927840848713,
        "amount": 38964.40394374445,
        "leverage": 3.0,
        "entry_time": 1774934848,
        "max_price": 0.0135,
        "min_price": 0.01325,
        "side": "SHORT"
      },
      {
        "symbol": "RIVERUSDT",
        "entry_price": 17.072,
        "margin": 172.0927840848713,
        "amount": 30.241234316694822,
        "leverage": 3.0,
        "entry_time": 1774934848,
        "max_price": 17.519,
        "min_price": 17.072,
        "side": "SHORT"
      },
      {
        "symbol": "GUSDT",
        "entry_price": 0.004272,
        "margin": 172.0927840848713,
        "amount": 120851.67421690404,
        "leverage": 3.0,
        "entry_time": 1774934848,
        "max_price": 0.004313,
        "min_price": 0.004272,
        "side": "SHORT"
      },
      {
        "symbol": "PIPPINUSDT",
        "entry_price": 0.06336,
        "margin": 172.0927840848713,
        "amount": 8148.3325797761045,
        "leverage": 3.0,
        "entry_time": 1774934848,
        "max_price": 0.06336,
        "min_price": 0.0549,
        "side": "SHORT"
      },
      {
        "symbol": "GUAUSDT",
        "entry_price": 0.37758,
        "margin": 172.0927840848713,
        "amount": 1367.3350078251335,
        "leverage": 3.0,
        "entry_time": 1774934848,
        "max_price": 0.38059,
        "min_price": 0.37758,
        "side": "SHORT"
      },
      {
        "symbol": "DUSDT",
        "entry_price": 0.006821,
        "margin": 172.0927840848713,
        "amount": 75689.5399874819,
        "leverage": 3.0,
        "entry_time": 1774934848,
        "max_price": 0.006821,
        "min_price": 0.006569,
        "side": "SHORT"
      },
      {
        "symbol": "USUSDT",
        "entry_price": 0.003908,
        "margin": 172.0927840848713,
        "amount": 132108.07376013664,
        "leverage": 3.0,
        "entry_time": 1774934848,
        "max_price": 0.004289,
        "min_price": 0.003908,
        "side": "SHORT"
      },
      {
        "symbol": "DAMUSDT",
        "entry_price": 0.03505,
        "margin": 172.0927840848713,
        "amount": 14729.767539361314,
        "leverage": 3.0,
        "entry_time": 1774934848,
        "max_price": 0.03673,
        "min_price": 0.03505,
        "side": "SHORT"
      },
      {
        "symbol": "BANUSDT",
        "entry_price": 0.06541,
        "margin": 172.0927840848713,
        "amount": 7892.9575333223365,
        "leverage": 3.0,
        "entry_time": 1774934848,
        "max_price": 0.06614,
        "min_price": 0.06541,
        "side": "SHORT"
      },
      {
        "symbol": "FHEUSDT",
        "entry_price": 0.01942,
        "margin": 172.0927840848713,
        "amount": 26584.879106828732,
        "leverage": 3.0,
        "entry_time": 1774934848,
        "max_price": 0.01968,
        "min_price": 0.01942,
        "side": "SHORT"
      }
    ],
    "last_trade_date": "2026-03-31",
    "total_invested": 0.0,
    "liquidation_count": 1
  },
  "6": {
    "balance": 1708.6385159442361,
    "positions": [
      {
        "symbol": "AIOTUSDT",
        "entry_price": 0.0135,
        "margin": 170.8638515944236,
        "amount": 37969.7447987608,
        "leverage": 3.0,
        "entry_time": 1774939846,
        "max_price": 0.0135,
        "min_price": 0.01344,
        "side": "SHORT"
      },
      {
        "symbol": "RIVERUSDT",
        "entry_price": 17.474,
        "margin": 170.8638515944236,
        "amount": 29.33452871599352,
        "leverage": 3.0,
        "entry_time": 1774939846,
        "max_price": 17.519,
        "min_price": 17.474,
        "side": "SHORT"
      },
      {
        "symbol": "GUSDT",
        "entry_price": 0.004313,
        "margin": 170.8638515944236,
        "amount": 118848.03032303983,
        "leverage": 3.0,
        "entry_time": 1774939846,
        "max_price": 0.004313,
        "min_price": 0.004291,
        "side": "SHORT"
      },
      {
        "symbol": "KERNELUSDT",
        "entry_price": 0.08645,
        "margin": 170.8638515944236,
        "amount": 5929.34129303957,
        "leverage": 3.0,
        "entry_time": 1774939846,
        "max_price": 0.08824,
        "min_price": 0.08645,
        "side": "SHORT"
      },
      {
        "symbol": "DAMUSDT",
        "entry_price": 0.0363,
        "margin": 170.8638515944236,
        "amount": 14120.979470613522,
        "leverage": 3.0,
        "entry_time": 1774939846,
        "max_price": 0.03673,
        "min_price": 0.0363,
        "side": "SHORT"
      },
      {
        "symbol": "USUSDT",
        "entry_price": 0.003994,
        "margin": 170.8638515944236,
        "amount": 128340.39929475983,
        "leverage": 3.0,
        "entry_time": 1774939846,
        "max_price": 0.004289,
        "min_price": 0.003994,
        "side": "SHORT"
      },
      {
        "symbol": "ONTUSDT",
        "entry_price": 0.0808,
        "margin": 170.8638515944236,
        "amount": 6343.954885931569,
        "leverage": 3.0,
        "entry_time": 1774939846,
        "max_price": 0.0808,
        "min_price": 0.0804,
        "side": "SHORT"
      },
      {
        "symbol": "BANUSDT",
        "entry_price": 0.06614,
        "margin": 170.8638515944236,
        "amount": 7750.099104676002,
        "leverage": 3.0,
        "entry_time": 1774939846,
        "max_price": 0.06614,
        "min_price": 0.06544,
        "side": "SHORT"
      },
      {
        "symbol": "FHEUSDT",
        "entry_price": 0.01968,
        "margin": 170.8638515944236,
        "amount": 26046.318840613352,
        "leverage": 3.0,
        "entry_time": 1774939846,
        "max_price": 0.01968,
        "min_price": 0.0196,
        "side": "SHORT"
      },
      {
        "symbol": "GUAUSDT",
        "entry_price": 0.38059,
        "margin": 170.8638515944236,
        "amount": 1346.8340071553926,
        "leverage": 3.0,
        "entry_time": 1774939846,
        "max_price": 0.38059,
        "min_price": 0.38009,
        "side": "SHORT"
      }
    ],
    "last_trade_date": "2026-03-31",
    "total_invested": 0.0,
    "liquidation_count": 0
  },
  "7": {
    "balance": 1494.0000568870307,
    "positions": [],
    "last_trade_date": "2026-03-31",
    "total_invested": 1000.0,
    "liquidation_count": 1
  },
  "8": {
    "balance": 902.6840637556262,
    "positions": [
      {
        "symbol": "AIOTUSDT",
        "entry_price": 0.01344,
        "margin": 90.26840637556262,
        "amount": 20149.197851688084,
        "leverage": 3.0,
        "entry_time": 1774944470,
        "max_price": 0.01344,
        "min_price": 0.01344,
        "side": "SHORT"
      },
      {
        "symbol": "RIVERUSDT",
        "entry_price": 17.519,
        "margin": 90.26840637556262,
        "amount": 15.457801194513836,
        "leverage": 3.0,
        "entry_time": 1774944470,
        "max_price": 17.519,
        "min_price": 17.519,
        "side": "SHORT"
      },
      {
        "symbol": "KERNELUSDT",
        "entry_price": 0.08824,
        "margin": 90.26840637556262,
        "amount": 3068.9621387883935,
        "leverage": 3.0,
        "entry_time": 1774944470,
        "max_price": 0.08824,
        "min_price": 0.08824,
        "side": "SHORT"
      },
      {
        "symbol": "GUSDT",
        "entry_price": 0.004291,
        "margin": 90.26840637556262,
        "amount": 63110.04873611929,
        "leverage": 3.0,
        "entry_time": 1774944470,
        "max_price": 0.004291,
        "min_price": 0.004291,
        "side": "SHORT"
      },
      {
        "symbol": "USUSDT",
        "entry_price": 0.004289,
        "margin": 90.26840637556262,
        "amount": 63139.477530120734,
        "leverage": 3.0,
        "entry_time": 1774944470,
        "max_price": 0.004289,
        "min_price": 0.004289,
        "side": "SHORT"
      },
      {
        "symbol": "BANUSDT",
        "entry_price": 0.06544,
        "margin": 90.26840637556262,
        "amount": 4138.22156367188,
        "leverage": 3.0,
        "entry_time": 1774944470,
        "max_price": 0.06544,
        "min_price": 0.06544,
        "side": "SHORT"
      },
      {
        "symbol": "FHEUSDT",
        "entry_price": 0.0196,
        "margin": 90.26840637556262,
        "amount": 13816.592812586116,
        "leverage": 3.0,
        "entry_time": 1774944470,
        "max_price": 0.0196,
        "min_price": 0.0196,
        "side": "SHORT"
      },
      {
        "symbol": "SKLUSDT",
        "entry_price": 0.00667,
        "margin": 90.26840637556262,
        "amount": 40600.48262768934,
        "leverage": 3.0,
        "entry_time": 1774944470,
        "max_price": 0.00667,
        "min_price": 0.00667,
        "side": "SHORT"
      },
      {
        "symbol": "TAKEUSDT",
        "entry_price": 0.01584,
        "margin": 90.26840637556262,
        "amount": 17096.289086280798,
        "leverage": 3.0,
        "entry_time": 1774944470,
        "max_price": 0.01584,
        "min_price": 0.01584,
        "side": "SHORT"
      },
      {
        "symbol": "ZBTUSDT",
        "entry_price": 0.08459,
        "margin": 90.26840637556262,
        "amount": 3201.385732671567,
        "leverage": 3.0,
        "entry_time": 1774944470,
        "max_price": 0.08459,
        "min_price": 0.08459,
        "side": "SHORT"
      }
    ],
    "last_trade_date": "2026-03-31",
    "total_invested": -1000.0,
    "liquidation_count": 1
  },
  "9": {
    "balance": 1091.103991320718,
    "positions": [
      {
        "symbol": "DUSDT",
        "entry_price": 0.007343,
        "margin": 109.1103991320718,
        "amount": 44577.311370858704,
        "leverage": 3.0,
        "entry_time": 1774864591,
        "max_price": 0.007808,
        "min_price": 0.006569,
        "side": "SHORT"
      },
      {
        "symbol": "NOMUSDT",
        "entry_price": 0.003364,
        "margin": 109.1103991320718,
        "amount": 97304.16093823289,
        "leverage": 3.0,
        "entry_time": 1774864591,
        "max_price": 0.003523,
        "min_price": 0.003217,
        "side": "SHORT"
      },
      {
        "symbol": "ONTUSDT",
        "entry_price": 0.0695,
        "margin": 109.1103991320718,
        "amount": 4709.801401384394,
        "leverage": 3.0,
        "entry_time": 1774864591,
        "max_price": 0.0841,
        "min_price": 0.0695,
        "side": "SHORT"
      },
      {
        "symbol": "DAMUSDT",
        "entry_price": 0.03298,
        "margin": 109.1103991320718,
        "amount": 9925.14243166208,
        "leverage": 3.0,
        "entry_time": 1774864591,
        "max_price": 0.03673,
        "min_price": 0.03243,
        "side": "SHORT"
      },
      {
        "symbol": "USUALUSDT",
        "entry_price": 0.01385,
        "margin": 109.1103991320718,
        "amount": 23634.021472650933,
        "leverage": 3.0,
        "entry_time": 1774864591,
        "max_price": 0.01389,
        "min_price": 0.01271,
        "side": "SHORT"
      },
      {
        "symbol": "SENTUSDT",
        "entry_price": 0.01913,
        "margin": 109.1103991320718,
        "amount": 17110.88329305883,
        "leverage": 3.0,
        "entry_time": 1774864591,
        "max_price": 0.01919,
        "min_price": 0.01801,
        "side": "SHORT"
      },
      {
        "symbol": "ONUSDT",
        "entry_price": 0.11272,
        "margin": 109.1103991320718,
        "amount": 2903.931843472458,
        "leverage": 3.0,
        "entry_time": 1774864591,
        "max_price": 0.11272,
        "min_price": 0.09707,
        "side": "SHORT"
      },
      {
        "symbol": "GOATUSDT",
        "entry_price": 0.01882,
        "margin": 109.1103991320718,
        "amount": 17392.73099873621,
        "leverage": 3.0,
        "entry_time": 1774864591,
        "max_price": 0.01891,
        "min_price": 0.01798,
        "side": "SHORT"
      },
      {
        "symbol": "TRUTHUSDT",
        "entry_price": 0.010113,
        "margin": 109.1103991320718,
        "amount": 32367.368475844498,
        "leverage": 3.0,
        "entry_time": 1774864591,
        "max_price": 0.010113,
        "min_price": 0.009848,
        "side": "SHORT"
      },
      {
        "symbol": "AGTUSDT",
        "entry_price": 0.007217,
        "margin": 109.1103991320718,
        "amount": 45355.57674881743,
        "leverage": 3.0,
        "entry_time": 1774864591,
        "max_price": 0.007441,
        "min_price": 0.007081,
        "side": "SHORT"
      }
    ],
    "last_trade_date": "2026-03-30",
    "total_invested": 0.0,
    "liquidation_count": 1
  },
  "10": {
    "balance": 981.2988581557032,
    "positions": [],
    "last_trade_date": "2026-03-30",
    "total_invested": -1000.0,
    "liquidation_count": 0
  },
  "11": {
    "balance": 1036.3740488175124,
    "positions": [
      {
        "symbol": "DUSDT",
        "entry_price": 0.007204,
        "margin": 103.63740488175124,
        "amount": 43158.2752144994,
        "leverage": 3.0,
        "entry_time": 1774868428,
        "max_price": 0.007808,
        "min_price": 0.006569,
        "side": "SHORT"
      },
      {
        "symbol": "NOMUSDT",
        "entry_price": 0.00339,
        "margin": 103.63740488175124,
        "amount": 91714.51759447012,
        "leverage": 3.0,
        "entry_time": 1774868428,
        "max_price": 0.003523,
        "min_price": 0.003217,
        "side": "SHORT"
      },
      {
        "symbol": "ONTUSDT",
        "entry_price": 0.0696,
        "margin": 103.63740488175124,
        "amount": 4467.129520765139,
        "leverage": 3.0,
        "entry_time": 1774868428,
        "max_price": 0.0841,
        "min_price": 0.0696,
        "side": "SHORT"
      },
      {
        "symbol": "USUALUSDT",
        "entry_price": 0.01389,
        "margin": 103.63740488175124,
        "amount": 22383.8887433588,
        "leverage": 3.0,
        "entry_time": 1774868428,
        "max_price": 0.01389,
        "min_price": 0.01271,
        "side": "SHORT"
      },
      {
        "symbol": "GOATUSDT",
        "entry_price": 0.01891,
        "margin": 103.63740488175124,
        "amount": 16441.682424392053,
        "leverage": 3.0,
        "entry_time": 1774868428,
        "max_price": 0.01891,
        "min_price": 0.01798,
        "side": "SHORT"
      },
      {
        "symbol": "DAMUSDT",
        "entry_price": 0.03246,
        "margin": 103.63740488175124,
        "amount": 9578.31838093819,
        "leverage": 3.0,
        "entry_time": 1774868428,
        "max_price": 0.03673,
        "min_price": 0.03243,
        "side": "SHORT"
      },
      {
        "symbol": "TRUTHUSDT",
        "entry_price": 0.010102,
        "margin": 103.63740488175124,
        "amount": 30777.293075158752,
        "leverage": 3.0,
        "entry_time": 1774868428,
        "max_price": 0.010109,
        "min_price": 0.009848,
        "side": "SHORT"
      },
      {
        "symbol": "AGTUSDT",
        "entry_price": 0.007233,
        "margin": 103.63740488175124,
        "amount": 42985.23636737919,
        "leverage": 3.0,
        "entry_time": 1774868428,
        "max_price": 0.007441,
        "min_price": 0.007081,
        "side": "SHORT"
      },
      {
        "symbol": "DOODUSDT",
        "entry_price": 0.003162,
        "margin": 103.63740488175124,
        "amount": 98327.70861646227,
        "leverage": 3.0,
        "entry_time": 1774868428,
        "max_price": 0.003162,
        "min_price": 0.002983,
        "side": "SHORT"
      },
      {
        "symbol": "VVVUSDT",
        "entry_price": 6.613,
        "margin": 103.63740488175124,
        "amount": 47.01530540530072,
        "leverage": 3.0,
        "entry_time": 1774868428,
        "max_price": 6.65,
        "min_price": 6.167,
        "side": "SHORT"
      }
    ],
    "last_trade_date": "2026-03-30",
    "total_invested": 0.0,
    "liquidation_count": 1
  },
  "12": {
    "balance": 1693.3805444852203,
    "positions": [],
    "last_trade_date": "2026-03-30",
    "total_invested": 2000.0,
    "liquidation_count": 1
  },
  "13": {
    "balance": 451.81753549307376,
    "positions": [
      {
        "symbol": "DUSDT",
        "entry_price": 0.007665,
        "margin": 45.18175354930737,
        "amount": 17683.66088035514,
        "leverage": 3.0,
        "entry_time": 1774876223,
        "max_price": 0.007665,
        "min_price": 0.006569,
        "side": "SHORT"
      },
      {
        "symbol": "NOMUSDT",
        "entry_price": 0.003217,
        "margin": 45.18175354930737,
        "amount": 42134.05677585395,
        "leverage": 3.0,
        "entry_time": 1774876223,
        "max_price": 0.003523,
        "min_price": 0.003217,
        "side": "SHORT"
      },
      {
        "symbol": "ONTUSDT",
        "entry_price": 0.0706,
        "margin": 45.18175354930737,
        "amount": 1919.904541755271,
        "leverage": 3.0,
        "entry_time": 1774876223,
        "max_price": 0.0841,
        "min_price": 0.0706,
        "side": "SHORT"
      },
      {
        "symbol": "USUALUSDT",
        "entry_price": 0.01384,
        "margin": 45.18175354930737,
        "amount": 9793.73270577472,
        "leverage": 3.0,
        "entry_time": 1774876223,
        "max_price": 0.01384,
        "min_price": 0.01271,
        "side": "SHORT"
      },
      {
        "symbol": "DAMUSDT",
        "entry_price": 0.03291,
        "margin": 45.18175354930737,
        "amount": 4118.664863200308,
        "leverage": 3.0,
        "entry_time": 1774876223,
        "max_price": 0.03673,
        "min_price": 0.03291,
        "side": "SHORT"
      },
      {
        "symbol": "GOATUSDT",
        "entry_price": 0.01879,
        "margin": 45.18175354930737,
        "amount": 7213.691359655249,
        "leverage": 3.0,
        "entry_time": 1774876223,
        "max_price": 0.01879,
        "min_price": 0.01798,
        "side": "SHORT"
      },
      {
        "symbol": "THEUSDT",
        "entry_price": 0.1151,
        "margin": 45.18175354930737,
        "amount": 1177.630413969784,
        "leverage": 3.0,
        "entry_time": 1774876223,
        "max_price": 0.1191,
        "min_price": 0.1142,
        "side": "SHORT"
      },
      {
        "symbol": "DOODUSDT",
        "entry_price": 0.00312,
        "margin": 45.18175354930737,
        "amount": 43443.99379741094,
        "leverage": 3.0,
        "entry_time": 1774876223,
        "max_price": 0.00313,
        "min_price": 0.002983,
        "side": "SHORT"
      },
      {
        "symbol": "AGTUSDT",
        "entry_price": 0.007233,
        "margin": 45.18175354930737,
        "amount": 18739.83971352442,
        "leverage": 3.0,
        "entry_time": 1774876223,
        "max_price": 0.007441,
        "min_price": 0.007081,
        "side": "SHORT"
      },
      {
        "symbol": "ONGUSDT",
        "entry_price": 0.0635,
        "margin": 45.18175354930737,
        "amount": 2134.5710338255453,
        "leverage": 3.0,
        "entry_time": 1774876223,
        "max_price": 0.06493,
        "min_price": 0.06191,
        "side": "SHORT"
      }
    ],
    "last_trade_date": "2026-03-30",
    "total_invested": 1000.0,
    "liquidation_count": 0
  },
  "14": {
    "balance": 903.148213284269,
    "positions": [
      {
        "symbol": "DUSDT",
        "entry_price": 0.007651,
        "margin": 90.3148213284269,
        "amount": 35412.94784803042,
        "leverage": 3.0,
        "entry_time": 1774882028,
        "max_price": 0.007651,
        "min_price": 0.006569,
        "side": "SHORT"
      },
      {
        "symbol": "NOMUSDT",
        "entry_price": 0.003328,
        "margin": 90.3148213284269,
        "amount": 81413.6009571156,
        "leverage": 3.0,
        "entry_time": 1774882028,
        "max_price": 0.003523,
        "min_price": 0.003259,
        "side": "SHORT"
      },
      {
        "symbol": "ONTUSDT",
        "entry_price": 0.0714,
        "margin": 90.3148213284269,
        "amount": 3794.74039195071,
        "leverage": 3.0,
        "entry_time": 1774882028,
        "max_price": 0.0841,
        "min_price": 0.0714,
        "side": "SHORT"
      },
      {
        "symbol": "BEATUSDT",
        "entry_price": 0.5465,
        "margin": 90.3148213284269,
        "amount": 495.78126987242587,
        "leverage": 3.0,
        "entry_time": 1774882028,
        "max_price": 0.5794,
        "min_price": 0.5167,
        "side": "SHORT"
      },
      {
        "symbol": "DAMUSDT",
        "entry_price": 0.03415,
        "margin": 90.3148213284269,
        "amount": 7933.952093273228,
        "leverage": 3.0,
        "entry_time": 1774882028,
        "max_price": 0.03673,
        "min_price": 0.03384,
        "side": "SHORT"
      },
      {
        "symbol": "THEUSDT",
        "entry_price": 0.1168,
        "margin": 90.3148213284269,
        "amount": 2319.7299998739786,
        "leverage": 3.0,
        "entry_time": 1774882028,
        "max_price": 0.1191,
        "min_price": 0.1142,
        "side": "SHORT"
      },
      {
        "symbol": "GOATUSDT",
        "entry_price": 0.01851,
        "margin": 90.3148213284269,
        "amount": 14637.734413035156,
        "leverage": 3.0,
        "entry_time": 1774882028,
        "max_price": 0.01855,
        "min_price": 0.01798,
        "side": "SHORT"
      },
      {
        "symbol": "BLESSUSDT",
        "entry_price": 0.005497,
        "margin": 90.3148213284269,
        "amount": 49289.51500550859,
        "leverage": 3.0,
        "entry_time": 1774882028,
        "max_price": 0.005565,
        "min_price": 0.005418,
        "side": "SHORT"
      },
      {
        "symbol": "KITEUSDT",
        "entry_price": 0.17528,
        "margin": 90.3148213284269,
        "amount": 1545.7808305869507,
        "leverage": 3.0,
        "entry_time": 1774882028,
        "max_price": 0.17536,
        "min_price": 0.15523,
        "side": "SHORT"
      },
      {
        "symbol": "CETUSUSDT",
        "entry_price": 0.02957,
        "margin": 90.3148213284269,
        "amount": 9162.81582635376,
        "leverage": 3.0,
        "entry_time": 1774882028,
        "max_price": 0.03011,
        "min_price": 0.02035,
        "side": "SHORT"
      }
    ],
    "last_trade_date": "2026-03-30",
    "total_invested": 0.0,
    "liquidation_count": 0
  },
  "15": {
    "balance": 735.8632599672048,
    "positions": [
      {
        "symbol": "NOMUSDT",
        "entry_price": 0.003405,
        "margin": 73.58632599672049,
        "amount": 64833.76739799162,
        "leverage": 3.0,
        "entry_time": 1774886300,
        "max_price": 0.003523,
        "min_price": 0.003259,
        "side": "SHORT"
      },
      {
        "symbol": "DUSDT",
        "entry_price": 0.00729,
        "margin": 73.58632599672049,
        "amount": 30282.43868177798,
        "leverage": 3.0,
        "entry_time": 1774886300,
        "max_price": 0.00729,
        "min_price": 0.006569,
        "side": "SHORT"
      },
      {
        "symbol": "ONTUSDT",
        "entry_price": 0.0759,
        "margin": 73.58632599672049,
        "amount": 2908.5504346529838,
        "leverage": 3.0,
        "entry_time": 1774886300,
        "max_price": 0.0841,
        "min_price": 0.0759,
        "side": "SHORT"
      },
      {
        "symbol": "THEUSDT",
        "entry_price": 0.1191,
        "margin": 73.58632599672049,
        "amount": 1853.5598487838915,
        "leverage": 3.0,
        "entry_time": 1774886300,
        "max_price": 0.1191,
        "min_price": 0.1142,
        "side": "SHORT"
      },
      {
        "symbol": "CETUSUSDT",
        "entry_price": 0.03011,
        "margin": 73.58632599672049,
        "amount": 7331.749518105661,
        "leverage": 3.0,
        "entry_time": 1774886300,
        "max_price": 0.03011,
        "min_price": 0.02035,
        "side": "SHORT"
      },
      {
        "symbol": "DAMUSDT",
        "entry_price": 0.03402,
        "margin": 73.58632599672049,
        "amount": 6489.094003238138,
        "leverage": 3.0,
        "entry_time": 1774886300,
        "max_price": 0.03673,
        "min_price": 0.03384,
        "side": "SHORT"
      },
      {
        "symbol": "ONGUSDT",
        "entry_price": 0.06397,
        "margin": 73.58632599672049,
        "amount": 3450.976676413342,
        "leverage": 3.0,
        "entry_time": 1774886300,
        "max_price": 0.06493,
        "min_price": 0.06191,
        "side": "SHORT"
      },
      {
        "symbol": "GOATUSDT",
        "entry_price": 0.01831,
        "margin": 73.58632599672049,
        "amount": 12056.743746049233,
        "leverage": 3.0,
        "entry_time": 1774886300,
        "max_price": 0.01855,
        "min_price": 0.01798,
        "side": "SHORT"
      },
      {
        "symbol": "BLESSUSDT",
        "entry_price": 0.005479,
        "margin": 73.58632599672049,
        "amount": 40291.83755980315,
        "leverage": 3.0,
        "entry_time": 1774886300,
        "max_price": 0.005565,
        "min_price": 0.005418,
        "side": "SHORT"
      },
      {
        "symbol": "DOODUSDT",
        "entry_price": 0.003092,
        "margin": 73.58632599672049,
        "amount": 71396.82341208326,
        "leverage": 3.0,
        "entry_time": 1774886300,
        "max_price": 0.00313,
        "min_price": 0.002983,
        "side": "SHORT"
      }
    ],
    "last_trade_date": "2026-03-30",
    "total_invested": 1000.0,
    "liquidation_count": 0
  },
  "16": {
    "balance": 642.172963874629,
    "positions": [
      {
        "symbol": "NOMUSDT",
        "entry_price": 0.003392,
        "margin": 64.2172963874629,
        "amount": 56795.95788985515,
        "leverage": 3.0,
        "entry_time": 1774889668,
        "max_price": 0.003523,
        "min_price": 0.003259,
        "side": "SHORT"
      },
      {
        "symbol": "ONTUSDT",
        "entry_price": 0.0803,
        "margin": 64.2172963874629,
        "amount": 2399.1517952974928,
        "leverage": 3.0,
        "entry_time": 1774889668,
        "max_price": 0.0841,
        "min_price": 0.0769,
        "side": "SHORT"
      },
      {
        "symbol": "DUSDT",
        "entry_price": 0.007183,
        "margin": 64.2172963874629,
        "amount": 26820.533086786672,
        "leverage": 3.0,
        "entry_time": 1774889668,
        "max_price": 0.007262,
        "min_price": 0.006569,
        "side": "SHORT"
      },
      {
        "symbol": "BEATUSDT",
        "entry_price": 0.5751,
        "margin": 64.2172963874629,
        "amount": 334.9885048902603,
        "leverage": 3.0,
        "entry_time": 1774889668,
        "max_price": 0.5794,
        "min_price": 0.5167,
        "side": "SHORT"
      },
      {
        "symbol": "CETUSUSDT",
        "entry_price": 0.03006,
        "margin": 64.2172963874629,
        "amount": 6408.9118151160565,
        "leverage": 3.0,
        "entry_time": 1774889668,
        "max_price": 0.03006,
        "min_price": 0.02035,
        "side": "SHORT"
      },
      {
        "symbol": "DAMUSDT",
        "entry_price": 0.03386,
        "margin": 64.2172963874629,
        "amount": 5689.660046142607,
        "leverage": 3.0,
        "entry_time": 1774889668,
        "max_price": 0.03673,
        "min_price": 0.03384,
        "side": "SHORT"
      },
      {
        "symbol": "GOATUSDT",
        "entry_price": 0.01855,
        "margin": 64.2172963874629,
        "amount": 10385.546585573513,
        "leverage": 3.0,
        "entry_time": 1774889668,
        "max_price": 0.01855,
        "min_price": 0.01798,
        "side": "SHORT"
      },
      {
        "symbol": "THEUSDT",
        "entry_price": 0.115,
        "margin": 64.2172963874629,
        "amount": 1675.2338188033796,
        "leverage": 3.0,
        "entry_time": 1774889668,
        "max_price": 0.118,
        "min_price": 0.1142,
        "side": "SHORT"
      },
      {
        "symbol": "STGUSDT",
        "entry_price": 0.2721,
        "margin": 64.2172963874629,
        "amount": 708.0187032796349,
        "leverage": 3.0,
        "entry_time": 1774889668,
        "max_price": 0.273,
        "min_price": 0.2605,
        "side": "SHORT"
      },
      {
        "symbol": "ONGUSDT",
        "entry_price": 0.06429,
        "margin": 64.2172963874629,
        "amount": 2996.607390922207,
        "leverage": 3.0,
        "entry_time": 1774889668,
        "max_price": 0.06493,
        "min_price": 0.06191,
        "side": "SHORT"
      }
    ],
    "last_trade_date": "2026-03-30",
    "total_invested": -1000.0,
    "liquidation_count": 0
  },
  "17": {
    "balance": 426.83403061649034,
    "positions": [
      {
        "symbol": "ONTUSDT",
        "entry_price": 0.0813,
        "margin": 42.68340306164903,
        "amount": 1575.0333233080826,
        "leverage": 3.0,
        "entry_time": 1774893193,
        "max_price": 0.0841,
        "min_price": 0.0769,
        "side": "SHORT"
      },
      {
        "symbol": "NOMUSDT",
        "entry_price": 0.003346,
        "margin": 42.68340306164903,
        "amount": 38269.6381305879,
        "leverage": 3.0,
        "entry_time": 1774893193,
        "max_price": 0.003523,
        "min_price": 0.003259,
        "side": "SHORT"
      },
      {
        "symbol": "DUSDT",
        "entry_price": 0.007153,
        "margin": 42.68340306164903,
        "amount": 17901.609001111017,
        "leverage": 3.0,
        "entry_time": 1774893193,
        "max_price": 0.007262,
        "min_price": 0.006569,
        "side": "SHORT"
      },
      {
        "symbol": "CETUSUSDT",
        "entry_price": 0.02931,
        "margin": 42.68340306164903,
        "amount": 4368.823240701027,
        "leverage": 3.0,
        "entry_time": 1774893193,
        "max_price": 0.02931,
        "min_price": 0.02035,
        "side": "SHORT"
      },
      {
        "symbol": "DAMUSDT",
        "entry_price": 0.03384,
        "margin": 42.68340306164903,
        "amount": 3783.9896331249142,
        "leverage": 3.0,
        "entry_time": 1774893193,
        "max_price": 0.03673,
        "min_price": 0.03384,
        "side": "SHORT"
      },
      {
        "symbol": "GOATUSDT",
        "entry_price": 0.01851,
        "margin": 42.68340306164903,
        "amount": 6917.893527009569,
        "leverage": 3.0,
        "entry_time": 1774893193,
        "max_price": 0.01852,
        "min_price": 0.01798,
        "side": "SHORT"
      },
      {
        "symbol": "BEATUSDT",
        "entry_price": 0.5794,
        "margin": 42.68340306164903,
        "amount": 221.00484843794806,
        "leverage": 3.0,
        "entry_time": 1774893193,
        "max_price": 0.5794,
        "min_price": 0.5167,
        "side": "SHORT"
      },
      {
        "symbol": "THEUSDT",
        "entry_price": 0.1144,
        "margin": 42.68340306164903,
        "amount": 1119.3200103579293,
        "leverage": 3.0,
        "entry_time": 1774893193,
        "max_price": 0.118,
        "min_price": 0.1142,
        "side": "SHORT"
      },
      {
        "symbol": "ONGUSDT",
        "entry_price": 0.06456,
        "margin": 42.68340306164903,
        "amount": 1983.4295102996762,
        "leverage": 3.0,
        "entry_time": 1774893193,
        "max_price": 0.06493,
        "min_price": 0.06191,
        "side": "SHORT"
      },
      {
        "symbol": "DOODUSDT",
        "entry_price": 0.003099,
        "margin": 42.68340306164903,
        "amount": 41319.84807516848,
        "leverage": 3.0,
        "entry_time": 1774893193,
        "max_price": 0.00313,
        "min_price": 0.002983,
        "side": "SHORT"
      }
    ],
    "last_trade_date": "2026-03-30",
    "total_invested": 0.0,
    "liquidation_count": 0
  },
  "18": {
    "balance": 1102.5735932679056,
    "positions": [
      {
        "symbol": "NOMUSDT",
        "entry_price": 0.003306,
        "margin": 110.25735932679056,
        "amount": 100052.05020579907,
        "leverage": 3.0,
        "entry_time": 1774896941,
        "max_price": 0.003523,
        "min_price": 0.003259,
        "side": "SHORT"
      },
      {
        "symbol": "DUSDT",
        "entry_price": 0.007262,
        "margin": 110.25735932679056,
        "amount": 45548.34453048357,
        "leverage": 3.0,
        "entry_time": 1774896941,
        "max_price": 0.007262,
        "min_price": 0.006569,
        "side": "SHORT"
      },
      {
        "symbol": "ONTUSDT",
        "entry_price": 0.0798,
        "margin": 110.25735932679056,
        "amount": 4145.013508525962,
        "leverage": 3.0,
        "entry_time": 1774896941,
        "max_price": 0.0841,
        "min_price": 0.0769,
        "side": "SHORT"
      },
      {
        "symbol": "DAMUSDT",
        "entry_price": 0.03508,
        "margin": 110.25735932679056,
        "amount": 9429.078619736936,
        "leverage": 3.0,
        "entry_time": 1774896941,
        "max_price": 0.03673,
        "min_price": 0.0349,
        "side": "SHORT"
      },
      {
        "symbol": "USUSDT",
        "entry_price": 0.003931,
        "margin": 110.25735932679056,
        "amount": 84144.51233283433,
        "leverage": 3.0,
        "entry_time": 1774896941,
        "max_price": 0.004289,
        "min_price": 0.003894,
        "side": "SHORT"
      },
      {
        "symbol": "THEUSDT",
        "entry_price": 0.1162,
        "margin": 110.25735932679056,
        "amount": 2846.5755419997568,
        "leverage": 3.0,
        "entry_time": 1774896941,
        "max_price": 0.118,
        "min_price": 0.1142,
        "side": "SHORT"
      },
      {
        "symbol": "BEATUSDT",
        "entry_price": 0.5601,
        "margin": 110.25735932679056,
        "amount": 590.5589680063769,
        "leverage": 3.0,
        "entry_time": 1774896941,
        "max_price": 0.5766,
        "min_price": 0.5167,
        "side": "SHORT"
      },
      {
        "symbol": "DOODUSDT",
        "entry_price": 0.003118,
        "margin": 110.25735932679056,
        "amount": 106084.69466977924,
        "leverage": 3.0,
        "entry_time": 1774896941,
        "max_price": 0.00313,
        "min_price": 0.002983,
        "side": "SHORT"
      },
      {
        "symbol": "ONGUSDT",
        "entry_price": 0.06412,
        "margin": 110.25735932679056,
        "amount": 5158.641266069428,
        "leverage": 3.0,
        "entry_time": 1774896941,
        "max_price": 0.06493,
        "min_price": 0.06191,
        "side": "SHORT"
      },
      {
        "symbol": "GOATUSDT",
        "entry_price": 0.01798,
        "margin": 110.25735932679056,
        "amount": 18396.66729590499,
        "leverage": 3.0,
        "entry_time": 1774896941,
        "max_price": 0.01852,
        "min_price": 0.01798,
        "side": "SHORT"
      }
    ],
    "last_trade_date": "2026-03-30",
    "total_invested": 1000.0,
    "liquidation_count": 0
  },
  "19": {
    "balance": 1062.6897817040815,
    "positions": [
      {
        "symbol": "NOMUSDT",
        "entry_price": 0.003307,
        "margin": 106.26897817040815,
        "amount": 96403.66934116252,
        "leverage": 3.0,
        "entry_time": 1774900522,
        "max_price": 0.003523,
        "min_price": 0.003259,
        "side": "SHORT"
      },
      {
        "symbol": "ONTUSDT",
        "entry_price": 0.082,
        "margin": 106.26897817040815,
        "amount": 3887.8894452588343,
        "leverage": 3.0,
        "entry_time": 1774900522,
        "max_price": 0.0841,
        "min_price": 0.0769,
        "side": "SHORT"
      },
      {
        "symbol": "DUSDT",
        "entry_price": 0.006871,
        "margin": 106.26897817040815,
        "amount": 46398.91347856563,
        "leverage": 3.0,
        "entry_time": 1774900522,
        "max_price": 0.007143,
        "min_price": 0.006569,
        "side": "SHORT"
      },
      {
        "symbol": "DAMUSDT",
        "entry_price": 0.03542,
        "margin": 106.26897817040815,
        "amount": 9000.76043227624,
        "leverage": 3.0,
        "entry_time": 1774900522,
        "max_price": 0.03673,
        "min_price": 0.0349,
        "side": "SHORT"
      },
      {
        "symbol": "USUSDT",
        "entry_price": 0.003903,
        "margin": 106.26897817040815,
        "amount": 81682.53510408005,
        "leverage": 3.0,
        "entry_time": 1774900522,
        "max_price": 0.004289,
        "min_price": 0.003894,
        "side": "SHORT"
      },
      {
        "symbol": "THEUSDT",
        "entry_price": 0.118,
        "margin": 106.26897817040815,
        "amount": 2701.753682298512,
        "leverage": 3.0,
        "entry_time": 1774900522,
        "max_price": 0.118,
        "min_price": 0.1142,
        "side": "SHORT"
      },
      {
        "symbol": "BEATUSDT",
        "entry_price": 0.5663,
        "margin": 106.26897817040815,
        "amount": 562.9647439717895,
        "leverage": 3.0,
        "entry_time": 1774900522,
        "max_price": 0.5766,
        "min_price": 0.5167,
        "side": "SHORT"
      },
      {
        "symbol": "DOODUSDT",
        "entry_price": 0.00313,
        "margin": 106.26897817040815,
        "amount": 101855.25064256371,
        "leverage": 3.0,
        "entry_time": 1774900522,
        "max_price": 0.00313,
        "min_price": 0.002983,
        "side": "SHORT"
      },
      {
        "symbol": "GOATUSDT",
        "entry_price": 0.01805,
        "margin": 106.26897817040815,
        "amount": 17662.43404494318,
        "leverage": 3.0,
        "entry_time": 1774900522,
        "max_price": 0.01852,
        "min_price": 0.01798,
        "side": "SHORT"
      },
      {
        "symbol": "ONGUSDT",
        "entry_price": 0.06412,
        "margin": 106.26897817040815,
        "amount": 4972.035784641679,
        "leverage": 3.0,
        "entry_time": 1774900522,
        "max_price": 0.06493,
        "min_price": 0.06191,
        "side": "SHORT"
      }
    ],
    "last_trade_date": "2026-03-30",
    "total_invested": 0.0,
    "liquidation_count": 0
  },
  "20": {
    "balance": 1357.6010808954493,
    "positions": [
      {
        "symbol": "NOMUSDT",
        "entry_price": 0.003386,
        "margin": 135.76010808954493,
        "amount": 120283.61614549166,
        "leverage": 3.0,
        "entry_time": 1774903313,
        "max_price": 0.003523,
        "min_price": 0.003259,
        "side": "SHORT"
      },
      {
        "symbol": "ONTUSDT",
        "entry_price": 0.0805,
        "margin": 135.76010808954493,
        "amount": 5059.382910169376,
        "leverage": 3.0,
        "entry_time": 1774903313,
        "max_price": 0.0841,
        "min_price": 0.0769,
        "side": "SHORT"
      },
      {
        "symbol": "DUSDT",
        "entry_price": 0.006832,
        "margin": 135.76010808954493,
        "amount": 59613.630601380966,
        "leverage": 3.0,
        "entry_time": 1774903313,
        "max_price": 0.007143,
        "min_price": 0.006569,
        "side": "SHORT"
      },
      {
        "symbol": "DAMUSDT",
        "entry_price": 0.03578,
        "margin": 135.76010808954493,
        "amount": 11382.90453517705,
        "leverage": 3.0,
        "entry_time": 1774903313,
        "max_price": 0.03673,
        "min_price": 0.0349,
        "side": "SHORT"
      },
      {
        "symbol": "USUSDT",
        "entry_price": 0.003894,
        "margin": 135.76010808954493,
        "amount": 104591.76278085126,
        "leverage": 3.0,
        "entry_time": 1774903313,
        "max_price": 0.004289,
        "min_price": 0.003894,
        "side": "SHORT"
      },
      {
        "symbol": "BEATUSDT",
        "entry_price": 0.5698,
        "margin": 135.76010808954493,
        "amount": 714.777683869138,
        "leverage": 3.0,
        "entry_time": 1774903313,
        "max_price": 0.5766,
        "min_price": 0.5167,
        "side": "SHORT"
      },
      {
        "symbol": "ONGUSDT",
        "entry_price": 0.06429,
        "margin": 135.76010808954493,
        "amount": 6335.049374220482,
        "leverage": 3.0,
        "entry_time": 1774903313,
        "max_price": 0.06493,
        "min_price": 0.06191,
        "side": "SHORT"
      },
      {
        "symbol": "GOATUSDT",
        "entry_price": 0.01798,
        "margin": 135.76010808954493,
        "amount": 22651.853407599265,
        "leverage": 3.0,
        "entry_time": 1774903313,
        "max_price": 0.01852,
        "min_price": 0.01798,
        "side": "SHORT"
      },
      {
        "symbol": "DOODUSDT",
        "entry_price": 0.00311,
        "margin": 135.76010808954493,
        "amount": 130958.30362335524,
        "leverage": 3.0,
        "entry_time": 1774903313,
        "max_price": 0.00311,
        "min_price": 0.002983,
        "side": "SHORT"
      },
      {
        "symbol": "ZBTUSDT",
        "entry_price": 0.0822,
        "margin": 135.76010808954493,
        "amount": 4954.748470421348,
        "leverage": 3.0,
        "entry_time": 1774903313,
        "max_price": 0.08459,
        "min_price": 0.07759,
        "side": "SHORT"
      }
    ],
    "last_trade_date": "2026-03-30",
    "total_invested": 0.0,
    "liquidation_count": 0
  },
  "21": {
    "balance": 1444.7162855268205,
    "positions": [
      {
        "symbol": "NOMUSDT",
        "entry_price": 0.003503,
        "margin": 144.47162855268203,
        "amount": 123726.77295405256,
        "leverage": 3.0,
        "entry_time": 1774906143,
        "max_price": 0.003523,
        "min_price": 0.003259,
        "side": "SHORT"
      },
      {
        "symbol": "ONTUSDT",
        "entry_price": 0.0817,
        "margin": 144.47162855268203,
        "amount": 5304.955760808398,
        "leverage": 3.0,
        "entry_time": 1774906143,
        "max_price": 0.0841,
        "min_price": 0.0769,
        "side": "SHORT"
      },
      {
        "symbol": "DUSDT",
        "entry_price": 0.006729,
        "margin": 144.47162855268203,
        "amount": 64409.999354740095,
        "leverage": 3.0,
        "entry_time": 1774906143,
        "max_price": 0.007143,
        "min_price": 0.006569,
        "side": "SHORT"
      },
      {
        "symbol": "DAMUSDT",
        "entry_price": 0.03565,
        "margin": 144.47162855268203,
        "amount": 12157.500298963425,
        "leverage": 3.0,
        "entry_time": 1774906143,
        "max_price": 0.03673,
        "min_price": 0.0349,
        "side": "SHORT"
      },
      {
        "symbol": "USUSDT",
        "entry_price": 0.003987,
        "margin": 144.47162855268203,
        "amount": 108707.01922699927,
        "leverage": 3.0,
        "entry_time": 1774906143,
        "max_price": 0.004289,
        "min_price": 0.003894,
        "side": "SHORT"
      },
      {
        "symbol": "BEATUSDT",
        "entry_price": 0.5766,
        "margin": 144.47162855268203,
        "amount": 751.673405581072,
        "leverage": 3.0,
        "entry_time": 1774906143,
        "max_price": 0.5766,
        "min_price": 0.5167,
        "side": "SHORT"
      },
      {
        "symbol": "GOATUSDT",
        "entry_price": 0.0182,
        "margin": 144.47162855268203,
        "amount": 23814.00470648605,
        "leverage": 3.0,
        "entry_time": 1774906143,
        "max_price": 0.01852,
        "min_price": 0.01798,
        "side": "SHORT"
      },
      {
        "symbol": "RIVERUSDT",
        "entry_price": 16.508,
        "margin": 144.47162855268203,
        "amount": 26.254839208750067,
        "leverage": 3.0,
        "entry_time": 1774906143,
        "max_price": 17.519,
        "min_price": 16.136,
        "side": "SHORT"
      },
      {
        "symbol": "ONGUSDT",
        "entry_price": 0.0648,
        "margin": 144.47162855268203,
        "amount": 6688.501321883428,
        "leverage": 3.0,
        "entry_time": 1774906143,
        "max_price": 0.06493,
        "min_price": 0.06191,
        "side": "SHORT"
      },
      {
        "symbol": "DOODUSDT",
        "entry_price": 0.003104,
        "margin": 144.47162855268203,
        "amount": 139631.08429705093,
        "leverage": 3.0,
        "entry_time": 1774906143,
        "max_price": 0.003104,
        "min_price": 0.002983,
        "side": "SHORT"
      }
    ],
    "last_trade_date": "2026-03-30",
    "total_invested": -1000.0,
    "liquidation_count": 0
  },
  "22": {
    "balance": 1833.2289737466,
    "positions": [
      {
        "symbol": "NOMUSDT",
        "entry_price": 0.003497,
        "margin": 183.32289737466002,
        "amount": 157268.7137901001,
        "leverage": 3.0,
        "entry_time": 1774908268,
        "max_price": 0.003523,
        "min_price": 0.003259,
        "side": "SHORT"
      },
      {
        "symbol": "ONTUSDT",
        "entry_price": 0.0814,
        "margin": 183.32289737466002,
        "amount": 6756.372139115234,
        "leverage": 3.0,
        "entry_time": 1774908268,
        "max_price": 0.0841,
        "min_price": 0.0769,
        "side": "SHORT"
      },
      {
        "symbol": "DUSDT",
        "entry_price": 0.006697,
        "margin": 183.32289737466002,
        "amount": 82121.65030968793,
        "leverage": 3.0,
        "entry_time": 1774908268,
        "max_price": 0.007143,
        "min_price": 0.006569,
        "side": "SHORT"
      },
      {
        "symbol": "DAMUSDT",
        "entry_price": 0.0355,
        "margin": 183.32289737466002,
        "amount": 15492.075834478313,
        "leverage": 3.0,
        "entry_time": 1774908268,
        "max_price": 0.03673,
        "min_price": 0.0349,
        "side": "SHORT"
      },
      {
        "symbol": "USUSDT",
        "entry_price": 0.003995,
        "margin": 183.32289737466002,
        "amount": 137664.2533476796,
        "leverage": 3.0,
        "entry_time": 1774908268,
        "max_price": 0.004289,
        "min_price": 0.003894,
        "side": "SHORT"
      },
      {
        "symbol": "GOATUSDT",
        "entry_price": 0.01813,
        "margin": 183.32289737466002,
        "amount": 30334.73205317044,
        "leverage": 3.0,
        "entry_time": 1774908268,
        "max_price": 0.01852,
        "min_price": 0.01798,
        "side": "SHORT"
      },
      {
        "symbol": "BEATUSDT",
        "entry_price": 0.5666,
        "margin": 183.32289737466002,
        "amount": 970.6471798870103,
        "leverage": 3.0,
        "entry_time": 1774908268,
        "max_price": 0.5666,
        "min_price": 0.5167,
        "side": "SHORT"
      },
      {
        "symbol": "ONGUSDT",
        "entry_price": 0.06445,
        "margin": 183.32289737466002,
        "amount": 8533.261320775488,
        "leverage": 3.0,
        "entry_time": 1774908268,
        "max_price": 0.06493,
        "min_price": 0.06191,
        "side": "SHORT"
      },
      {
        "symbol": "RIVERUSDT",
        "entry_price": 16.199,
        "margin": 183.32289737466002,
        "amount": 33.950780426197916,
        "leverage": 3.0,
        "entry_time": 1774908268,
        "max_price": 17.519,
        "min_price": 16.136,
        "side": "SHORT"
      },
      {
        "symbol": "ZBTUSDT",
        "entry_price": 0.08253,
        "margin": 183.32289737466002,
        "amount": 6663.863954004362,
        "leverage": 3.0,
        "entry_time": 1774908268,
        "max_price": 0.08459,
        "min_price": 0.07759,
        "side": "SHORT"
      }
    ],
    "last_trade_date": "2026-03-30",
    "total_invested": -2000.0,
    "liquidation_count": 0
  },
  "23": {
    "balance": 1128.3689100629526,
    "positions": [
      {
        "symbol": "ONTUSDT",
        "entry_price": 0.0837,
        "margin": 112.83689100629526,
        "amount": 4044.3330109783246,
        "leverage": 3.0,
        "entry_time": 1774913672,
        "max_price": 0.0841,
        "min_price": 0.0769,
        "side": "SHORT"
      },
      {
        "symbol": "NOMUSDT",
        "entry_price": 0.003466,
        "margin": 112.83689100629526,
        "amount": 97666.091465345,
        "leverage": 3.0,
        "entry_time": 1774913672,
        "max_price": 0.003523,
        "min_price": 0.003259,
        "side": "SHORT"
      },
      {
        "symbol": "DUSDT",
        "entry_price": 0.006612,
        "margin": 112.83689100629526,
        "amount": 51196.411527357195,
        "leverage": 3.0,
        "entry_time": 1774913672,
        "max_price": 0.007143,
        "min_price": 0.006569,
        "side": "SHORT"
      },
      {
        "symbol": "DAMUSDT",
        "entry_price": 0.03527,
        "margin": 112.83689100629526,
        "amount": 9597.69415987768,
        "leverage": 3.0,
        "entry_time": 1774913672,
        "max_price": 0.03673,
        "min_price": 0.0349,
        "side": "SHORT"
      },
      {
        "symbol": "USUSDT",
        "entry_price": 0.003945,
        "margin": 112.83689100629526,
        "amount": 85807.52167779107,
        "leverage": 3.0,
        "entry_time": 1774913672,
        "max_price": 0.004289,
        "min_price": 0.003894,
        "side": "SHORT"
      },
      {
        "symbol": "FHEUSDT",
        "entry_price": 0.0186,
        "margin": 112.83689100629526,
        "amount": 18199.498549402462,
        "leverage": 3.0,
        "entry_time": 1774913672,
        "max_price": 0.02005,
        "min_price": 0.0186,
        "side": "SHORT"
      },
      {
        "symbol": "GOATUSDT",
        "entry_price": 0.01798,
        "margin": 112.83689100629526,
        "amount": 18827.067464899097,
        "leverage": 3.0,
        "entry_time": 1774913672,
        "max_price": 0.01852,
        "min_price": 0.01798,
        "side": "SHORT"
      },
      {
        "symbol": "RIVERUSDT",
        "entry_price": 16.136,
        "margin": 112.83689100629526,
        "amount": 20.978598972414837,
        "leverage": 3.0,
        "entry_time": 1774913672,
        "max_price": 17.519,
        "min_price": 16.136,
        "side": "SHORT"
      },
      {
        "symbol": "ONGUSDT",
        "entry_price": 0.06493,
        "margin": 112.83689100629526,
        "amount": 5213.471015230029,
        "leverage": 3.0,
        "entry_time": 1774913672,
        "max_price": 0.06493,
        "min_price": 0.06191,
        "side": "SHORT"
      },
      {
        "symbol": "DOODUSDT",
        "entry_price": 0.0031,
        "margin": 112.83689100629526,
        "amount": 109196.99129641477,
        "leverage": 3.0,
        "entry_time": 1774913672,
        "max_price": 0.0031,
        "min_price": 0.002983,
        "side": "SHORT"
      }
    ],
    "last_trade_date": "2026-03-30",
    "total_invested": -2000.0,
    "liquidation_count": 0
  },
  "S_CHASE": {
    "balance": 311.76327485059454,
    "positions": [
      {
        "symbol": "RIVERUSDT",
        "entry_price": 16.508,
        "margin": 100.0,
        "amount": 18.17300702689605,
        "leverage": 3.0,
        "entry_time": 1774906143,
        "max_price": 17.519,
        "min_price": 16.136,
        "side": "LONG"
      },
      {
        "symbol": "DOODUSDT",
        "entry_price": 0.003089,
        "margin": 100.0,
        "amount": 97118.8086759469,
        "leverage": 3.0,
        "entry_time": 1774911523,
        "max_price": 0.0031,
        "min_price": 0.002983,
        "side": "LONG"
      },
      {
        "symbol": "FHEUSDT",
        "entry_price": 0.01835,
        "margin": 100.0,
        "amount": 16348.77384196185,
        "leverage": 3.0,
        "entry_time": 1774911523,
        "max_price": 0.02005,
        "min_price": 0.01835,
        "side": "LONG"
      },
      {
        "symbol": "CYSUSDT",
        "entry_price": 0.3917,
        "margin": 100.0,
        "amount": 765.8922644881287,
        "leverage": 3.0,
        "entry_time": 1774927910,
        "max_price": 0.3917,
        "min_price": 0.3485,
        "side": "LONG"
      },
      {
        "symbol": "BANUSDT",
        "entry_price": 0.0661,
        "margin": 100.0,
        "amount": 4538.57791225416,
        "leverage": 3.0,
        "entry_time": 1774927910,
        "max_price": 0.06614,
        "min_price": 0.06541,
        "side": "LONG"
      },
      {
        "symbol": "AIOTUSDT",
        "entry_price": 0.01079,
        "margin": 100.0,
        "amount": 27803.521779425395,
        "leverage": 3.0,
        "entry_time": 1774927910,
        "max_price": 0.0135,
        "min_price": 0.01079,
        "side": "LONG"
      },
      {
        "symbol": "GUSDT",
        "entry_price": 0.004151,
        "margin": 100.0,
        "amount": 72271.74174897614,
        "leverage": 3.0,
        "entry_time": 1774927910,
        "max_price": 0.004313,
        "min_price": 0.004151,
        "side": "LONG"
      },
      {
        "symbol": "PIPPINUSDT",
        "entry_price": 0.06336,
        "margin": 100.0,
        "amount": 4734.848484848485,
        "leverage": 3.0,
        "entry_time": 1774934848,
        "max_price": 0.06336,
        "min_price": 0.0549,
        "side": "LONG"
      },
      {
        "symbol": "GUAUSDT",
        "entry_price": 0.37758,
        "margin": 100.0,
        "amount": 794.533608771651,
        "leverage": 3.0,
        "entry_time": 1774934848,
        "max_price": 0.38059,
        "min_price": 0.37758,
        "side": "LONG"
      },
      {
        "symbol": "ONTUSDT",
        "entry_price": 0.0808,
        "margin": 100.0,
        "amount": 3712.871287128713,
        "leverage": 3.0,
        "entry_time": 1774939846,
        "max_price": 0.0808,
        "min_price": 0.0804,
        "side": "LONG"
      },
      {
        "symbol": "KERNELUSDT",
        "entry_price": 0.08645,
        "margin": 100.0,
        "amount": 3470.213996529786,
        "leverage": 3.0,
        "entry_time": 1774939846,
        "max_price": 0.08824,
        "min_price": 0.08645,
        "side": "LONG"
      },
      {
        "symbol": "TAKEUSDT",
        "entry_price": 0.01584,
        "margin": 100.0,
        "amount": 18939.39393939394,
        "leverage": 3.0,
        "entry_time": 1774944470,
        "max_price": 0.01584,
        "min_price": 0.01584,
        "side": "LONG"
      },
      {
        "symbol": "SKLUSDT",
        "entry_price": 0.00667,
        "margin": 100.0,
        "amount": 44977.51124437781,
        "leverage": 3.0,
        "entry_time": 1774944470,
        "max_price": 0.00667,
        "min_price": 0.00667,
        "side": "LONG"
      }
    ],
    "prev_top10": [
      "RIVERUSDT",
      "USUSDT",
      "SKLUSDT",
      "TAKEUSDT",
      "ZBTUSDT",
      "FHEUSDT",
      "AIOTUSDT",
      "BANUSDT",
      "KERNELUSDT",
      "GUSDT"
    ],
    "total_invested": 1000.0,
    "liquidation_count": 127,
    "closed_count": 1021,
    "wins": 419,
    "accumulated_pnl": 102.82139733106125
  }
}